frontend/dist/4ffb837ab66ba0021e7a.png
frontend/dist/bundle.js
frontend/dist/bundle.js.LICENSE.txt
frontend/dist/index.html
reliquery_ui/__init__.py
reliquery_ui/main.py
reliquery_ui/routers/__init__.py
reliquery_ui/routers/relics.py
reliquery_ui-0.2.8.data/scripts/reliquery-ui
reliquery_ui-0.2.8.dist-info/LICENSE
reliquery_ui-0.2.8.dist-info/METADATA
reliquery_ui-0.2.8.dist-info/WHEEL
reliquery_ui-0.2.8.dist-info/top_level.txt
reliquery_ui-0.2.8.dist-info/RECORD
