Metadata-Version: 2.1
Name: reliquery-ui
Version: 0.2.8
Summary: Science's Artifact Antiformat
Home-page: https://github.com/The-Dev-Effect/reliquery-ui
Author: The Dev Effect
Author-email: company@thedeveffect.com
License: MIT OR Apache-2.0
Platform: UNKNOWN
License-File: LICENSE
Requires-Dist: reliquery (>=0.3.1)
Requires-Dist: numpy (>=1.16)
Requires-Dist: black (>=21.4b)
Requires-Dist: fastapi[all]
Requires-Dist: requests
Requires-Dist: uvicorn
